langchain_aisdk_adapter/__init__.py
langchain_aisdk_adapter/adapter.py
langchain_aisdk_adapter/config.py
langchain_aisdk_adapter/emitter.py
langchain_aisdk_adapter/factory.py
langchain_aisdk_adapter/models.py
langchain_aisdk_adapter/utils.py
langchain_aisdk_adapter-0.0.1a1.dist-info/licenses/LICENSE
langchain_aisdk_adapter-0.0.1a1.dist-info/METADATA
langchain_aisdk_adapter-0.0.1a1.dist-info/WHEEL
langchain_aisdk_adapter-0.0.1a1.dist-info/top_level.txt
langchain_aisdk_adapter-0.0.1a1.dist-info/RECORD
