Metadata-Version: 2.4
Name: langchain-aisdk-adapter
Version: 0.0.1a1
Summary: A Python package that converts LangChain/LangGraph event streams to AI SDK UI Stream Protocol format
Author-email: Egoalpha <yao_yuan@live.com>
Maintainer-email: Egoalpha <yao_yuan@live.com>
License: Apache-2.0
Project-URL: Homepage, https://github.com/lointain/langchain_aisdk_adapter
Project-URL: Repository, https://github.com/lointain/langchain_aisdk_adapter
Project-URL: Documentation, https://github.com/lointain/langchain_aisdk_adapter#readme
Project-URL: Bug Tracker, https://github.com/lointain/langchain_aisdk_adapter/issues
Keywords: langchain,ai-sdk,stream,protocol,adapter,langgraph,ai,llm,fastapi
Classifier: Development Status :: 3 - Alpha
Classifier: Intended Audience :: Developers
Classifier: License :: OSI Approved :: Apache Software License
Classifier: Operating System :: OS Independent
Classifier: Programming Language :: Python :: 3
Classifier: Programming Language :: Python :: 3.8
Classifier: Programming Language :: Python :: 3.9
Classifier: Programming Language :: Python :: 3.10
Classifier: Programming Language :: Python :: 3.11
Classifier: Programming Language :: Python :: 3.12
Classifier: Topic :: Software Development :: Libraries :: Python Modules
Classifier: Topic :: Scientific/Engineering :: Artificial Intelligence
Requires-Python: <4.0,>=3.9.0
License-File: LICENSE
Requires-Dist: pydantic>=2.0.0
Requires-Dist: langchain-core>=0.1.0
Requires-Dist: typing-extensions>=4.0.0
Requires-Dist: python-dotenv>=1.0.0
Provides-Extra: dev
Requires-Dist: pytest>=7.0.0; extra == "dev"
Requires-Dist: pytest-asyncio>=0.21.0; extra == "dev"
Requires-Dist: pytest-cov>=4.0.0; extra == "dev"
Requires-Dist: black>=23.0.0; extra == "dev"
Requires-Dist: isort>=5.12.0; extra == "dev"
Requires-Dist: flake8>=6.0.0; extra == "dev"
Requires-Dist: mypy>=1.0.0; extra == "dev"
Requires-Dist: pre-commit>=3.0.0; extra == "dev"
Provides-Extra: test
Requires-Dist: pytest>=7.0.0; extra == "test"
Requires-Dist: pytest-asyncio>=0.21.0; extra == "test"
Requires-Dist: pytest-cov>=4.0.0; extra == "test"
Provides-Extra: examples
Requires-Dist: langchain>=0.1.0; extra == "examples"
Requires-Dist: langgraph>=0.1.0; extra == "examples"
Requires-Dist: langchain-openai>=0.1.0; extra == "examples"
Requires-Dist: openai>=1.0.0; extra == "examples"
Provides-Extra: web
Requires-Dist: fastapi>=0.104.0; extra == "web"
Requires-Dist: uvicorn[standard]>=0.24.0; extra == "web"
Requires-Dist: langchain>=0.1.0; extra == "web"
Requires-Dist: langchain-openai>=0.1.0; extra == "web"
Requires-Dist: openai>=1.0.0; extra == "web"
Provides-Extra: docs
Requires-Dist: mkdocs>=1.5.0; extra == "docs"
Requires-Dist: mkdocs-material>=9.0.0; extra == "docs"
Requires-Dist: mkdocstrings[python]>=0.22.0; extra == "docs"
Provides-Extra: all
Requires-Dist: langchain>=0.1.0; extra == "all"
Requires-Dist: langgraph>=0.1.0; extra == "all"
Requires-Dist: langchain-openai>=0.1.0; extra == "all"
Requires-Dist: openai>=1.0.0; extra == "all"
Requires-Dist: fastapi>=0.104.0; extra == "all"
Requires-Dist: uvicorn[standard]>=0.24.0; extra == "all"
Requires-Dist: pytest>=7.0.0; extra == "all"
Requires-Dist: pytest-asyncio>=0.21.0; extra == "all"
Requires-Dist: pytest-cov>=4.0.0; extra == "all"
Requires-Dist: black>=23.0.0; extra == "all"
Requires-Dist: isort>=5.12.0; extra == "all"
Requires-Dist: flake8>=6.0.0; extra == "all"
Requires-Dist: mypy>=1.0.0; extra == "all"
Requires-Dist: pre-commit>=3.0.0; extra == "all"
Requires-Dist: mkdocs>=1.5.0; extra == "all"
Requires-Dist: mkdocs-material>=9.0.0; extra == "all"
Requires-Dist: mkdocstrings[python]>=0.22.0; extra == "all"
Dynamic: license-file
